Workbook

Sheet ⚙ Config
A1: PARAMÈTRES DE REPORTING — Consolidation mensuelle charges
A2: Modifier uniquement les cellules en BLEU. Le reste du fichier se met à jour automatiquement.
A4: Année de reporting | B4: 2024 | C4: Exercice couvert par ce fichier
A5: Mois en cours (n°) | B5: 10 | C5: Ex : 10 = Octobre (mise à jour en cours)
A6: Dernier mois clôturé | B6: Septembre 2024 | C6: Libellé du dernier mois validé
A7: Contrôleur de gestion | B7: Johan | C7: Responsable de la mise à jour
A8: Email VP Finance | B8: vpfinance@cybelangel.com | C8: Destinataire du rapport mensuel
A9: Seuil alerte écart (k€) | B9: 1 | C9: Tolérance max entre Synthèse et onglets sources
A12: LÉGENDE DES COULEURS (norme financière)
A13: ■ | B13: BLEU — Saisie manuelle / input utilisateur (données Sage)
A14: ■ | B14: NOIR — Formule de calcul automatique
A15: ■ | B15: VERT — Lien vers un autre onglet (cross-sheet)
A16: ■ | B16: ORANGE — Zone d'alerte / contrôle à vérifier

Sheet RH
A1: Charges — RH | Jan–Sep 2024 (k€) ⚡ Version automatisée
A2: Poste de charge | B2: Catégorie | C2: Jan 2024 | D2: Fév 2024 | E2: Mar 2024 | F2: Avr 2024 | G2: Mai 2024 | H2: Jun 2024 | I2: Jul 2024 | J2: Aoû 2024 | K2: Sep 2024 | L2: Total YTD
A3: Salaires & charges sociales
A4: Salaires fixes — tech & produit | B4: Salaires & charges sociales | C4: 410 | D4: 410 | E4: 415 | F4: 415 | G4: 420 | H4: 420 | I4: 435 | J4: 435 | K4: 440 | L4: =SUM(C4:K4) -> 3800
A5: Salaires fixes — sales & marketing | B5: Salaires & charges sociales | C5: 185 | D5: 185 | E5: 188 | F5: 188 | G5: 192 | H5: 192 | I5: 198 | J5: 198 | K5: 200 | L5: =SUM(C5:K5) -> 1726
A6: Salaires fixes — G&A | B6: Salaires & charges sociales | C6: 95 | D6: 95 | E6: 97 | F6: 97 | G6: 98 | H6: 98 | I6: 102 | J6: 102 | K6: 104 | L6: =SUM(C6:K6) -> 888
A7: Charges patronales | B7: Salaires & charges sociales | C7: 138 | D7: 138 | E7: 140 | F7: 140 | G7: 142 | H7: 142 | I7: 147 | J7: 147 | K7: 149 | L7: =SUM(C7:K7) -> 1283
A8: Primes variables — sales | B8: Salaires & charges sociales | C8: 18 | D8: 12 | E8: 22 | F8: 14 | G8: 25 | H8: 31 | I8: 19 | J8: 14 | K8: 28 | L8: =SUM(C8:K8) -> 183
A9: Sous-total Salaires & charges sociales | C9: =C4+C5+C6+C7+C8 -> 846 | D9: =D4+D5+D6+D7+D8 -> 840 | E9: =E4+E5+E6+E7+E8 -> 862 | F9: =F4+F5+F6+F7+F8 -> 854 | G9: =G4+G5+G6+G7+G8 -> 877 | H9: =H4+H5+H6+H7+H8 -> 883 | I9: =I4+I5+I6+I7+I8 -> 901 | J9: =J4+J5+J6+J7+J8 -> 896 | K9: =K4+K5+K6+K7+K8 -> 921 | L9: =SUM(C9:K9) -> 7880
A10: Recrutement & formation
A11: Frais de recrutement (cabinets) | B11: Recrutement & formation | C11: 8 | D11: 0 | E11: 12 | F11: 0 | G11: 15 | H11: 0 | I11: 8 | J11: 0 | K11: 12 | L11: =SUM(C11:K11) -> 55
A12: Formations & certifications | B12: Recrutement & formation | C12: 3 | D12: 3 | E12: 3 | F12: 3 | G12: 4 | H12: 4 | I12: 3 | J12: 3 | K12: 3 | L12: =SUM(C12:K12) -> 29
A13: Sous-total Recrutement & formation | C13: =C11+C12 -> 11 | D13: =D11+D12 -> 3 | E13: =E11+E12 -> 15 | F13: =F11+F12 -> 3 | G13: =G11+G12 -> 19 | H13: =H11+H12 -> 4 | I13: =I11+I12 -> 11 | J13: =J11+J12 -> 3 | K13: =K11+K12 -> 15 | L13: =SUM(C13:K13) -> 84
A14: Autres charges RH
A15: Tickets restaurant & avantages | B15: Autres charges RH | C15: 14 | D15: 14 | E15: 14 | F15: 14 | G15: 15 | H15: 15 | I15: 15 | J15: 15 | K15: 15 | L15: =SUM(C15:K15) -> 131
A16: Médecine du travail & mutuelle | B16: Autres charges RH | C16: 8 | D16: 8 | E16: 8 | F16: 8 | G16: 8 | H16: 8 | I16: 8 | J16: 8 | K16: 8 | L16: =SUM(C16:K16) -> 72
A17: Licences outils RH (ATS, HRIS) | B17: Autres charges RH | C17: 6 | D17: 6 | E17: 6 | F17: 6 | G17: 7 | H17: 7 | I17: 7 | J17: 7 | K17: 7 | L17: =SUM(C17:K17) -> 59
A18: Sous-total Autres charges RH | C18: =C15+C16+C17 -> 28 | D18: =D15+D16+D17 -> 28 | E18: =E15+E16+E17 -> 28 | F18: =F15+F16+F17 -> 28 | G18: =G15+G16+G17 -> 30 | H18: =H15+H16+H17 -> 30 | I18: =I15+I16+I17 -> 30 | J18: =J15+J16+J17 -> 30 | K18: =K15+K16+K17 -> 30 | L18: =SUM(C18:K18) -> 262
A19: TOTAL RH | C19: =C9+C13+C18 -> 885 | D19: =D9+D13+D18 -> 871 | E19: =E9+E13+E18 -> 905 | F19: =F9+F13+F18 -> 885 | G19: =G9+G13+G18 -> 926 | H19: =H9+H13+H18 -> 917 | I19: =I9+I13+I18 -> 942 | J19: =J9+J13+J18 -> 929 | K19: =K9+K13+K18 -> 966 | L19: =SUM(C19:K19) -> 8226
A22: ⚡ ZONE D'IMPORT AUTOMATIQUE — RH — Coller ici l'export Sage (CSV mensuel)
A23: → Coller ici l'export CSV RH depuis Sage (une colonne par mois). Power Automate dépose ce tableau automatiquement à partir du mois prochain.
A24: Poste de charge | B24: Catégorie | C24: Jan 2024 | D24: Fév 2024 | E24: Mar 2024 | F24: Avr 2024 | G24: Mai 2024 | H24: Jun 2024 | I24: Jul 2024 | J24: Aoû 2024 | K24: Sep 2024 | L24: CTRL

Sheet Tech
A1: Charges — Tech | Jan–Sep 2024 (k€) ⚡ Version automatisée
A2: Poste de charge | B2: Catégorie | C2: Jan 2024 | D2: Fév 2024 | E2: Mar 2024 | F2: Avr 2024 | G2: Mai 2024 | H2: Jun 2024 | I2: Jul 2024 | J2: Aoû 2024 | K2: Sep 2024 | L2: Total YTD
A3: Infrastructure & cloud
A4: AWS / Azure — prod | B4: Infrastructure & cloud | C4: 62 | D4: 63 | E4: 65 | F4: 66 | G4: 68 | H4: 71 | I4: 73 | J4: 74 | K4: 77 | L4: =SUM(C4:K4) -> 619
A5: AWS / Azure — dev & staging | B5: Infrastructure & cloud | C5: 18 | D5: 18 | E5: 19 | F5: 19 | G5: 20 | H5: 20 | I5: 21 | J5: 21 | K5: 22 | L5: =SUM(C5:K5) -> 178
A6: CDN & sécurité infra | B6: Infrastructure & cloud | C6: 8 | D6: 8 | E6: 8 | F6: 8 | G6: 9 | H6: 9 | I6: 9 | J6: 9 | K6: 9 | L6: =SUM(C6:K6) -> 77
A7: Sous-total Infrastructure & cloud | C7: =C4+C5+C6 -> 88 | D7: =D4+D5+D6 -> 89 | E7: =E4+E5+E6 -> 92 | F7: =F4+F5+F6 -> 93 | G7: =G4+G5+G6 -> 97 | H7: =H4+H5+H6 -> 100 | I7: =I4+I5+I6 -> 103 | J7: =J4+J5+J6 -> 104 | K7: =K4+K5+K6 -> 108 | L7: =SUM(C7:K7) -> 874
A8: Licences & SaaS Tech
A9: GitHub / GitLab | B9: Licences & SaaS Tech | C9: 4 | D9: 4 | E9: 4 | F9: 4 | G9: 4 | H9: 4 | I9: 4 | J9: 4 | K9: 4 | L9: =SUM(C9:K9) -> 36
A10: Datadog / monitoring | B10: Licences & SaaS Tech | C10: 12 | D10: 12 | E10: 13 | F10: 13 | G10: 13 | H10: 14 | I10: 14 | J10: 14 | K10: 15 | L10: =SUM(C10:K10) -> 120
A11: Licences data / enrichissement | B11: Licences & SaaS Tech | C11: 22 | D11: 22 | E11: 22 | F11: 24 | G11: 24 | H11: 24 | I11: 26 | J11: 26 | K11: 26 | L11: =SUM(C11:K11) -> 216
A12: Outils IA & LLM (API) | B12: Licences & SaaS Tech | C12: 5 | D12: 6 | E12: 7 | F12: 9 | G12: 11 | H12: 13 | I12: 15 | J12: 17 | K12: 19 | L12: =SUM(C12:K12) -> 102
A13: Sous-total Licences & SaaS Tech | C13: =C9+C10+C11+C12 -> 43 | D13: =D9+D10+D11+D12 -> 44 | E13: =E9+E10+E11+E12 -> 46 | F13: =F9+F10+F11+F12 -> 50 | G13: =G9+G10+G11+G12 -> 52 | H13: =H9+H10+H11+H12 -> 55 | I13: =I9+I10+I11+I12 -> 59 | J13: =J9+J10+J11+J12 -> 61 | K13: =K9+K10+K11+K12 -> 64 | L13: =SUM(C13:K13) -> 474
A14: Prestataires & sous-traitance
A15: Développeurs freelance | B15: Prestataires & sous-traitance | C15: 35 | D15: 35 | E15: 0 | F15: 0 | G15: 42 | H15: 42 | I15: 0 | J15: 0 | K15: 38 | L15: =SUM(C15:K15) -> 192
A16: Pentest & audits sécu | B16: Prestataires & sous-traitance | C16: 0 | D16: 0 | E16: 18 | F16: 0 | G16: 0 | H16: 0 | I16: 20 | J16: 0 | K16: 0 | L16: =SUM(C16:K16) -> 38
A17: Sous-total Prestataires & sous-traitance | C17: =C15+C16 -> 35 | D17: =D15+D16 -> 35 | E17: =E15+E16 -> 18 | F17: =F15+F16 -> 0 | G17: =G15+G16 -> 42 | H17: =H15+H16 -> 42 | I17: =I15+I16 -> 20 | J17: =J15+J16 -> 0 | K17: =K15+K16 -> 38 | L17: =SUM(C17:K17) -> 230
A18: TOTAL Tech | C18: =C7+C13+C17 -> 166 | D18: =D7+D13+D17 -> 168 | E18: =E7+E13+E17 -> 156 | F18: =F7+F13+F17 -> 143 | G18: =G7+G13+G17 -> 191 | H18: =H7+H13+H17 -> 197 | I18: =I7+I13+I17 -> 182 | J18: =J7+J13+J17 -> 165 | K18: =K7+K13+K17 -> 210 | L18: =SUM(C18:K18) -> 1578
A21: ⚡ ZONE D'IMPORT AUTOMATIQUE — Tech — Coller ici l'export Sage (CSV mensuel)
A22: → Coller ici l'export CSV Tech depuis Sage. Inclut AWS (facture directe), licences SaaS, et PO prestataires.
A23: Poste de charge | B23: Catégorie | C23: Jan 2024 | D23: Fév 2024 | E23: Mar 2024 | F23: Avr 2024 | G23: Mai 2024 | H23: Jun 2024 | I23: Jul 2024 | J23: Aoû 2024 | K23: Sep 2024 | L23: CTRL

Sheet S&M
A1: Charges — S&M | Jan–Sep 2024 (k€) ⚡ Version automatisée
A2: Poste de charge | B2: Catégorie | C2: Jan 2024 | D2: Fév 2024 | E2: Mar 2024 | F2: Avr 2024 | G2: Mai 2024 | H2: Jun 2024 | I2: Jul 2024 | J2: Aoû 2024 | K2: Sep 2024 | L2: Total YTD
A3: Marketing
A4: Événements & salons | B4: Marketing | C4: 0 | D4: 25 | E4: 0 | F4: 18 | G4: 0 | H4: 32 | I4: 0 | J4: 0 | K4: 45 | L4: =SUM(C4:K4) -> 120
A5: Digital marketing & SEO | B5: Marketing | C5: 15 | D5: 15 | E5: 16 | F5: 16 | G5: 17 | H5: 17 | I5: 18 | J5: 18 | K5: 19 | L5: =SUM(C5:K5) -> 151
A6: Contenu & production créa | B6: Marketing | C6: 8 | D6: 8 | E6: 9 | F6: 9 | G6: 10 | H6: 10 | I6: 10 | J6: 10 | K6: 11 | L6: =SUM(C6:K6) -> 85
A7: Relations presse & RP | B7: Marketing | C7: 5 | D7: 5 | E7: 5 | F7: 5 | G7: 5 | H7: 5 | I7: 5 | J7: 5 | K7: 5 | L7: =SUM(C7:K7) -> 45
A8: Sous-total Marketing | C8: =C4+C5+C6+C7 -> 28 | D8: =D4+D5+D6+D7 -> 53 | E8: =E4+E5+E6+E7 -> 30 | F8: =F4+F5+F6+F7 -> 48 | G8: =G4+G5+G6+G7 -> 32 | H8: =H4+H5+H6+H7 -> 64 | I8: =I4+I5+I6+I7 -> 33 | J8: =J4+J5+J6+J7 -> 33 | K8: =K4+K5+K6+K7 -> 80 | L8: =SUM(C8:K8) -> 401
A9: Sales
A10: Commissions & incentives | B10: Sales | C10: 28 | D10: 19 | E10: 34 | F10: 22 | G10: 38 | H10: 47 | I10: 29 | J10: 22 | K10: 43 | L10: =SUM(C10:K10) -> 282
A11: Déplacements commerciaux | B11: Sales | C11: 12 | D11: 14 | E11: 16 | F11: 11 | G11: 18 | H11: 22 | I11: 9 | J11: 8 | K11: 19 | L11: =SUM(C11:K11) -> 129
A12: CRM & sales tools (SF, Outreach…) | B12: Sales | C12: 14 | D12: 14 | E12: 14 | F12: 14 | G12: 14 | H12: 14 | I12: 14 | J12: 14 | K12: 14 | L12: =SUM(C12:K12) -> 126
A13: SDR — data enrichment tools | B13: Sales | C13: 4 | D13: 4 | E13: 4 | F13: 4 | G13: 5 | H13: 5 | I13: 5 | J13: 5 | K13: 5 | L13: =SUM(C13:K13) -> 41
A14: Sous-total Sales | C14: =C10+C11+C12+C13 -> 58 | D14: =D10+D11+D12+D13 -> 51 | E14: =E10+E11+E12+E13 -> 68 | F14: =F10+F11+F12+F13 -> 51 | G14: =G10+G11+G12+G13 -> 75 | H14: =H10+H11+H12+H13 -> 88 | I14: =I10+I11+I12+I13 -> 57 | J14: =J10+J11+J12+J13 -> 49 | K14: =K10+K11+K12+K13 -> 81 | L14: =SUM(C14:K14) -> 578
A15: Customer Success
A16: CS tools & plateformes | B16: Customer Success | C16: 6 | D16: 6 | E16: 6 | F16: 6 | G16: 6 | H16: 6 | I16: 7 | J16: 7 | K16: 7 | L16: =SUM(C16:K16) -> 57
A17: Formation clients & onboarding | B17: Customer Success | C17: 4 | D17: 4 | E17: 5 | F17: 5 | G17: 5 | H17: 6 | I17: 5 | J17: 5 | K17: 6 | L17: =SUM(C17:K17) -> 45
A18: Sous-total Customer Success | C18: =C16+C17 -> 10 | D18: =D16+D17 -> 10 | E18: =E16+E17 -> 11 | F18: =F16+F17 -> 11 | G18: =G16+G17 -> 11 | H18: =H16+H17 -> 12 | I18: =I16+I17 -> 12 | J18: =J16+J17 -> 12 | K18: =K16+K17 -> 13 | L18: =SUM(C18:K18) -> 102
A19: TOTAL S&M | C19: =C8+C14+C18 -> 96 | D19: =D8+D14+D18 -> 114 | E19: =E8+E14+E18 -> 109 | F19: =F8+F14+F18 -> 110 | G19: =G8+G14+G18 -> 118 | H19: =H8+H14+H18 -> 164 | I19: =I8+I14+I18 -> 102 | J19: =J8+J14+J18 -> 94 | K19: =K8+K14+K18 -> 174 | L19: =SUM(C19:K19) -> 1081
A22: ⚡ ZONE D'IMPORT AUTOMATIQUE — S&M — Coller ici l'export Sage (CSV mensuel)
A23: → Coller ici l'export CSV S&M depuis Sage. Commissions issues de Salesforce (réconcilier avec ADP).
A24: Poste de charge | B24: Catégorie | C24: Jan 2024 | D24: Fév 2024 | E24: Mar 2024 | F24: Avr 2024 | G24: Mai 2024 | H24: Jun 2024 | I24: Jul 2024 | J24: Aoû 2024 | K24: Sep 2024 | L24: CTRL

Sheet G&A
A1: Charges — G&A | Jan–Sep 2024 (k€) ⚡ Version automatisée
A2: Poste de charge | B2: Catégorie | C2: Jan 2024 | D2: Fév 2024 | E2: Mar 2024 | F2: Avr 2024 | G2: Mai 2024 | H2: Jun 2024 | I2: Jul 2024 | J2: Aoû 2024 | K2: Sep 2024 | L2: Total YTD
A3: Frais généraux
A4: Loyer & charges locatives | B4: Frais généraux | C4: 38 | D4: 38 | E4: 38 | F4: 38 | G4: 38 | H4: 38 | I4: 38 | J4: 38 | K4: 38 | L4: =SUM(C4:K4) -> 342
A5: Téléphonie & internet | B5: Frais généraux | C5: 4 | D5: 4 | E5: 4 | F5: 4 | G5: 4 | H5: 4 | I5: 4 | J5: 4 | K5: 4 | L5: =SUM(C5:K5) -> 36
A6: Fournitures & petits équipements | B6: Frais généraux | C6: 3 | D6: 2 | E6: 4 | F6: 2 | G6: 3 | H6: 5 | I6: 3 | J6: 2 | K6: 4 | L6: =SUM(C6:K6) -> 28
A7: Charges locatives refacturées | B7: Frais généraux | C7: 38 | D7: 38 | E7: 38 | F7: 38 | G7: 38 | H7: 38 | I7: 38 | J7: 38 | K7: 38 | L7: =SUM(C7:K7) -> 342
A8: Sous-total Frais généraux | C8: =C4+C5+C6+C7 -> 83 | D8: =D4+D5+D6+D7 -> 82 | E8: =E4+E5+E6+E7 -> 84 | F8: =F4+F5+F6+F7 -> 82 | G8: =G4+G5+G6+G7 -> 83 | H8: =H4+H5+H6+H7 -> 85 | I8: =I4+I5+I6+I7 -> 83 | J8: =J4+J5+J6+J7 -> 82 | K8: =K4+K5+K6+K7 -> 84 | L8: =SUM(C8:K8) -> 748
A9: Juridique & finance
A10: Honoraires avocats | B10: Juridique & finance | C10: 8 | D10: 0 | E10: 0 | F10: 12 | G10: 0 | H10: 0 | I10: 8 | J10: 0 | K10: 0 | L10: =SUM(C10:K10) -> 28
A11: Audit & commissariat aux comptes | B11: Juridique & finance | C11: 0 | D11: 0 | E11: 0 | F11: 0 | G11: 0 | H11: 22 | I11: 0 | J11: 0 | K11: 0 | L11: =SUM(C11:K11) -> 22
A12: Banque & frais financiers | B12: Juridique & finance | C12: 3 | D12: 3 | E12: 3 | F12: 3 | G12: 3 | H12: 3 | I12: 3 | J12: 3 | K12: 3 | L12: =SUM(C12:K12) -> 27
A13: Assurances | B13: Juridique & finance | C13: 6 | D13: 6 | E13: 6 | F13: 6 | G13: 6 | H13: 6 | I13: 6 | J13: 6 | K13: 6 | L13: =SUM(C13:K13) -> 54
A14: Sous-total Juridique & finance | C14: =C10+C11+C12+C13 -> 17 | D14: =D10+D11+D12+D13 -> 9 | E14: =E10+E11+E12+E13 -> 9 | F14: =F10+F11+F12+F13 -> 21 | G14: =G10+G11+G12+G13 -> 9 | H14: =H10+H11+H12+H13 -> 31 | I14: =I10+I11+I12+I13 -> 17 | J14: =J10+J11+J12+J13 -> 9 | K14: =K10+K11+K12+K13 -> 9 | L14: =SUM(C14:K14) -> 131
A15: IT G&A
A16: Licences Microsoft 365 | B16: IT G&A | C16: 5 | D16: 5 | E16: 5 | F16: 5 | G16: 5 | H16: 5 | I16: 5 | J16: 5 | K16: 5 | L16: =SUM(C16:K16) -> 45
A17: Licences Slack, Notion, Figma… | B17: IT G&A | C17: 4 | D17: 4 | E17: 4 | F17: 4 | G17: 4 | H17: 4 | I17: 4 | J17: 4 | K17: 4 | L17: =SUM(C17:K17) -> 36
A18: Sous-total IT G&A | C18: =C16+C17 -> 9 | D18: =D16+D17 -> 9 | E18: =E16+E17 -> 9 | F18: =F16+F17 -> 9 | G18: =G16+G17 -> 9 | H18: =H16+H17 -> 9 | I18: =I16+I17 -> 9 | J18: =J16+J17 -> 9 | K18: =K16+K17 -> 9 | L18: =SUM(C18:K18) -> 81
A19: TOTAL G&A | C19: =C8+C14+C18 -> 109 | D19: =D8+D14+D18 -> 100 | E19: =E8+E14+E18 -> 102 | F19: =F8+F14+F18 -> 112 | G19: =G8+G14+G18 -> 101 | H19: =H8+H14+H18 -> 125 | I19: =I8+I14+I18 -> 109 | J19: =J8+J14+J18 -> 100 | K19: =K8+K14+K18 -> 102 | L19: =SUM(C19:K19) -> 960
A22: ⚡ ZONE D'IMPORT AUTOMATIQUE — G&A — Coller ici l'export Sage (CSV mensuel)
A23: → Coller ici l'export CSV G&A depuis Sage. Honoraires avocats et audit : vérifier factures ponctuelles.
A24: Poste de charge | B24: Catégorie | C24: Jan 2024 | D24: Fév 2024 | E24: Mar 2024 | F24: Avr 2024 | G24: Mai 2024 | H24: Jun 2024 | I24: Jul 2024 | J24: Aoû 2024 | K24: Sep 2024 | L24: CTRL

Sheet ✅ Synthèse
A1: ✅ SYNTHÈSE CHARGES — Jan–Sep 2024 | 100% formules — mise à jour automatique (k€)
A2: Les valeurs ci-dessous sont liées par formule aux onglets sources. Toute modification dans RH / Tech / S&M / G&A est répercutée instantanément.
A3: Département | B3: Catégorie | C3: Jan 2024 | D3: Fév 2024 | E3: Mar 2024 | F3: Avr 2024 | G3: Mai 2024 | H3: Jun 2024 | I3: Jul 2024 | J3: Aoû 2024 | K3: Sep 2024 | L3: Total YTD | M3: % du total
A4: RH | B4: Total RH | C4: =RH!C19 -> 885 | D4: =RH!D19 -> 871 | E4: =RH!E19 -> 905 | F4: =RH!F19 -> 885 | G4: =RH!G19 -> 926 | H4: =RH!H19 -> 917 | I4: =RH!I19 -> 942 | J4: =RH!J19 -> 929 | K4: =RH!K19 -> 966 | L4: =SUM(C4:K4) -> 8226 | M4: =L4/L8 -> 0.69447024
A5: Tech | B5: Total Tech | C5: =Tech!C18 -> 166 | D5: =Tech!D18 -> 168 | E5: =Tech!E18 -> 156 | F5: =Tech!F18 -> 143 | G5: =Tech!G18 -> 191 | H5: =Tech!H18 -> 197 | I5: =Tech!I18 -> 182 | J5: =Tech!J18 -> 165 | K5: =Tech!K18 -> 210 | L5: =SUM(C5:K5) -> 1578 | M5: =L5/L8 -> 0.13322077
A6: S&M | B6: Total S&M | C6: ='S&M'!C19 -> 96 | D6: ='S&M'!D19 -> 114 | E6: ='S&M'!E19 -> 109 | F6: ='S&M'!F19 -> 110 | G6: ='S&M'!G19 -> 118 | H6: ='S&M'!H19 -> 164 | I6: ='S&M'!I19 -> 102 | J6: ='S&M'!J19 -> 94 | K6: ='S&M'!K19 -> 174 | L6: =SUM(C6:K6) -> 1081 | M6: =L6/L8 -> 0.091262136
A7: G&A | B7: Total G&A | C7: ='G&A'!C19 -> 109 | D7: ='G&A'!D19 -> 100 | E7: ='G&A'!E19 -> 102 | F7: ='G&A'!F19 -> 112 | G7: ='G&A'!G19 -> 101 | H7: ='G&A'!H19 -> 125 | I7: ='G&A'!I19 -> 109 | J7: ='G&A'!J19 -> 100 | K7: ='G&A'!K19 -> 102 | L7: =SUM(C7:K7) -> 960 | M7: =L7/L8 -> 0.081046855
A8: TOTAL CHARGES | C8: =SUM(C4:C7) -> 1256 | D8: =SUM(D4:D7) -> 1253 | E8: =SUM(E4:E7) -> 1272 | F8: =SUM(F4:F7) -> 1250 | G8: =SUM(G4:G7) -> 1336 | H8: =SUM(H4:H7) -> 1403 | I8: =SUM(I4:I7) -> 1335 | J8: =SUM(J4:J7) -> 1288 | K8: =SUM(K4:K7) -> 1452 | L8: =SUM(C8:K8) -> 11845 | M8: 100.0%

Sheet Contrôles
A1: CONTRÔLES AUTOMATIQUES — Cohérence Synthèse ↔ Onglets sources
A2: Si une cellule affiche ⚠ ÉCART, corriger l'onglet source avant d'envoyer le rapport.
A3: Département | B3: Contrôle | C3: Valeur Synthèse | D3: Valeur Onglet source | E3: Écart (k€) | F3: Statut
A4: RH | B4: Total YTD = Synthèse YTD | C4: ='✅ Synthèse'!L4 -> 8226 | D4: =RH!L19 -> 8226 | E4: =C4-D4 -> 0 | F4: =IF(ABS(E4)<=1,"✅ OK","⚠ ÉCART : "&TEXT(E4,"#,##0")&" k€") -> ✅ OK
A5: Tech | B5: Total YTD = Synthèse YTD | C5: ='✅ Synthèse'!L5 -> 1578 | D5: =Tech!L18 -> 1578 | E5: =C5-D5 -> 0 | F5: =IF(ABS(E5)<=1,"✅ OK","⚠ ÉCART : "&TEXT(E5,"#,##0")&" k€") -> ✅ OK
A6: S&M | B6: Total YTD = Synthèse YTD | C6: ='✅ Synthèse'!L6 -> 1081 | D6: ='S&M'!L19 -> 1081 | E6: =C6-D6 -> 0 | F6: =IF(ABS(E6)<=1,"✅ OK","⚠ ÉCART : "&TEXT(E6,"#,##0")&" k€") -> ✅ OK
A7: G&A | B7: Total YTD = Synthèse YTD | C7: ='✅ Synthèse'!L7 -> 960 | D7: ='G&A'!L19 -> 960 | E7: =C7-D7 -> 0 | F7: =IF(ABS(E7)<=1,"✅ OK","⚠ ÉCART : "&TEXT(E7,"#,##0")&" k€") -> ✅ OK
A9: GLOBAL — Total charges | C9: ='✅ Synthèse'!L8 -> 11845 | D9: =RH!L19+Tech!L18+'S&M'!L19+'G&A'!L19 -> 11845 | E9: =C9-D9 -> 0 | F9: =IF(ABS(E9)=0,"✅ FICHIER VALIDÉ","⚠ VÉRIFIER : "&TEXT(ABS(E9),"#,##0")&" k€ d'écart") -> ✅ FICHIER VALIDÉ
A11: CHECKLIST MENSUELLE — À vérifier avant envoi au VP Finance
A12: □ Tous les onglets sources mis à jour avec l'export Sage du mois
A13: □ Cellule G9 (statut global) affiche ✅ FICHIER VALIDÉ
A14: □ Charges patronales ADP vérifiées dans onglet RH (ligne 7)
A15: □ Export PDF généré via Fichier → Exporter (ou Power Automate si configuré)
A16: □ Email envoyé au VP Finance avec PDF en pièce jointe

Sheet 📋 Note process
A1: PROCESSUS DE CONSOLIDATION MENSUELLE — VERSION AUTOMATISÉE
A4: AVANT (2h / mois — état initial)
A5: 1. Récupérer les exports Sage manuellement (PDF ou écran) ~10 min
A6: 2. Re-saisir colonne par colonne dans 4 onglets ~45 min
A7: 3. Copier les totaux EN VALEUR dans Synthèse (désynchro possible) ~30 min
A8: 4. Vérifier à la main la cohérence (pas de formule de contrôle) ~30 min
A9: 5. Exporter PDF et envoyer par email ~15 min
A10: TOTAL ~2h
A12: APRÈS — Quick wins Excel (15 min / mois)
A13: 1. Ouvrir le fichier et coller l'export Sage dans les zones Import ~5 min
A14: 2. Vérifier l'onglet 🔍 Contrôles (statut global = ✅ FICHIER VALIDÉ) ~3 min
A15: 3. Exporter PDF et envoyer (ou automatique via Power Automate) ~2 min
... A31: ⚠ Audit & honoraires : ligne G&A uniquement sur facture reçue et validée
